fieldbook
