Metadata-Version: 1.1
Name: django-fieldbook
Version: 0.0.3
Summary: A simple Django app for interacting with the Fieldbook.com API.
Home-page: https://github.com/bsab/django-fieldbook
Author: bsab
Author-email: tino.saba@gmail.com
License: MIT License
Platform: UNKNOWN
Classifier: Development Status :: 4 - Beta
Classifier: Environment :: Web Environment
Classifier: Framework :: Django
Classifier: Intended Audience :: Developers
Classifier: License :: OSI Approved :: MIT License
Classifier: Operating System :: OS Independent
Classifier: Programming Language :: Python
Classifier: Programming Language :: Python :: 2
Classifier: Programming Language :: Python :: 2.7
Classifier: Topic :: Internet :: WWW/HTTP
Classifier: Topic :: Software Development :: Libraries
